tepimport/__init__.py
tepimport/download.py
tepimport/tepimport.py
tepimport-0.0.3.dist-info/LICENSE
tepimport-0.0.3.dist-info/METADATA
tepimport-0.0.3.dist-info/WHEEL
tepimport-0.0.3.dist-info/top_level.txt
tepimport-0.0.3.dist-info/RECORD
