Metadata-Version: 2.1
Name: tepimport
Version: 0.0.3
Summary: Utility for quickly downloading and loading the Tennessee Eastman Process data set
Home-page: https://github.com/hsaafan/TEPImport
Author: Hussein Saafan
Author-email: hsaafan@uwaterloo.ca
License: UNKNOWN
Platform: UNKNOWN
Classifier: Programming Language :: Python :: 3
Classifier: License :: OSI Approved :: MIT License
Classifier: Operating System :: OS Independent
Requires-Python: >=3.6
License-File: LICENSE
Requires-Dist: numpy
Requires-Dist: pyreadr
Requires-Dist: webdriver-manager
Requires-Dist: selenium
